torch_time_stretch/__init__.py
torch_time_stretch/main.py
torch_time_stretch-1.0.3.dist-info/LICENSE
torch_time_stretch-1.0.3.dist-info/METADATA
torch_time_stretch-1.0.3.dist-info/WHEEL
torch_time_stretch-1.0.3.dist-info/top_level.txt
torch_time_stretch-1.0.3.dist-info/RECORD
