Metadata-Version: 2.1
Name: torch-time-stretch
Version: 1.0.3
Summary: UNKNOWN
Home-page: https://github.com/KentoNishi/torch-time-stretch
Author: KentoNishi
Author-email: kento24gs@outlook.com
License: UNKNOWN
Platform: UNKNOWN
Classifier: Programming Language :: Python :: 3
Classifier: License :: OSI Approved :: MIT License
Classifier: Operating System :: OS Independent
Requires-Python: >=3.4
License-File: LICENSE
Requires-Dist: torch (>=1.7.0)
Requires-Dist: torchaudio (>=0.7.0)
Requires-Dist: primePy (>=1.3)
